sample_pool/__init__.py
sample_pool/experiment.py
sample_pool-1.0.0.dist-info/LICENSE
sample_pool-1.0.0.dist-info/WHEEL
sample_pool-1.0.0.dist-info/METADATA
sample_pool-1.0.0.dist-info/RECORD
