Metadata-Version: 2.1
Name: sample-pool
Version: 1.0.0
Summary: A Python package for calculating aliquot size based on sample intensity
License: MIT
Keywords: protein sequence,modification,mass spectrometry
Author: Toan Phung
Author-email: toan.phungkhoiquoctoan@gmail.com
Requires-Python: >=3.9,<4.0
Classifier: License :: OSI Approved :: MIT License
Classifier: Programming Language :: Python :: 3
Classifier: Programming Language :: Python :: 3.10
Classifier: Programming Language :: Python :: 3.9
Requires-Dist: pandas (>=1.4.3,<2.0.0)
